hifiyaml/__init__.py
hifiyaml/core.py
hifiyaml-0.1.7.dist-info/licenses/LICENSE
hifiyaml-0.1.7.dist-info/METADATA
hifiyaml-0.1.7.dist-info/WHEEL
hifiyaml-0.1.7.dist-info/top_level.txt
hifiyaml-0.1.7.dist-info/RECORD
