Metadata-Version: 2.4
Name: hifiyaml
Version: 0.1.7
Summary: High-fidelity YAML parser that preserves formatting
Author-email: Guoqing Ge <Guoqing.Ge@noaa.gov>
Project-URL: Homepage, https://github.com/hifiyaml/hifiyaml/wiki
Project-URL: Source, https://github.com/hifiyaml/hifiyaml
Project-URL: Tracker, https://github.com/hifiyaml/hifiyaml/issues
Requires-Python: >=3.9
License-File: LICENSE
Dynamic: license-file
